idzip/__init__.py
idzip/_stream.py
idzip/api.py
idzip/caching.py
idzip/command.py
idzip/compressor.py
idzip/decompressor.py
python_idzip-0.3.10.dist-info/licenses/LICENSE
python_idzip-0.3.10.dist-info/METADATA
python_idzip-0.3.10.dist-info/WHEEL
python_idzip-0.3.10.dist-info/entry_points.txt
python_idzip-0.3.10.dist-info/top_level.txt
python_idzip-0.3.10.dist-info/RECORD
