Metadata-Version: 2.4
Name: python-idzip
Version: 0.3.10
Summary: DictZip - Random Access gzip files
Author-email: Rik Faith <john.doe@example.com>
Maintainer-email: Dan Bauman <dan@bauman.space>
License: MIT
Project-URL: Homepage, https://github.com/bauman/python-idzip
Project-URL: Repository, https://github.com/bauman/python-idzip
Project-URL: Issues, https://github.com/bauman/python-idzip/issues
Requires-Python: >=3.8
License-File: LICENSE
Dynamic: license-file
